emoji_fzf/__init__.py
emoji_fzf/emoji_fzf.py
emoji_fzf/emoji_fzf_emojilib.py
emoji_fzf-0.10.0.dist-info/METADATA
emoji_fzf-0.10.0.dist-info/WHEEL
emoji_fzf-0.10.0.dist-info/entry_points.txt
emoji_fzf-0.10.0.dist-info/top_level.txt
emoji_fzf-0.10.0.dist-info/RECORD
