Metadata-Version: 2.1
Name: emoji-fzf
Version: 0.10.0
Summary: Emoji searcher for use with fzf
Home-page: https://github.com/noahp/emoji-fzf
Author: Noah Pendleton
Author-email: 2538614+noahp@users.noreply.github.com
Project-URL: Code, https://github.com/noahp/emoji-fzf
Project-URL: Issue tracker, https://github.com/noahp/emoji-fzf/issues
Classifier: License :: OSI Approved :: MIT License
Classifier: Programming Language :: Python :: 3.8
Classifier: Programming Language :: Python :: 3.9
Classifier: Programming Language :: Python :: 3.10
Classifier: Programming Language :: Python :: 3.11
Classifier: Programming Language :: Python :: 3.12
Classifier: Programming Language :: Python :: 3.13
Classifier: Operating System :: OS Independent
Requires-Dist: click
